sphinxcontrib_apiblueprint-0.9.0-py2.7-nspkg.pth
sphinxcontrib/apiblueprint/__init__.py
sphinxcontrib/apiblueprint/addnodes.py
sphinxcontrib/apiblueprint/directive.py
sphinxcontrib/apiblueprint/domain.py
sphinxcontrib/apiblueprint/translator.py
sphinxcontrib/apiblueprint/utils.py
sphinxcontrib_apiblueprint-0.9.0.dist-info/DESCRIPTION.rst
sphinxcontrib_apiblueprint-0.9.0.dist-info/METADATA
sphinxcontrib_apiblueprint-0.9.0.dist-info/RECORD
sphinxcontrib_apiblueprint-0.9.0.dist-info/WHEEL
sphinxcontrib_apiblueprint-0.9.0.dist-info/metadata.json
sphinxcontrib_apiblueprint-0.9.0.dist-info/namespace_packages.txt
sphinxcontrib_apiblueprint-0.9.0.dist-info/top_level.txt
