Metadata-Version: 2.0
Name: sphinxcontrib-apiblueprint
Version: 0.9.0
Summary: Sphinx extension to create API docs using API Blueprint
Home-page: https://github.com/tk0miya/sphinxcontrib-apiblueprint
Author: Takeshi KOMIYA
Author-email: i.tkomiya@gmail.com
License: BSD
Platform: any
Classifier: Development Status :: 4 - Beta
Classifier: Environment :: Console
Classifier: Framework :: Sphinx :: Extension
Classifier: Intended Audience :: Developers
Classifier: License :: OSI Approved :: BSD License
Classifier: Operating System :: OS Independent
Classifier: Programming Language :: Python
Classifier: Programming Language :: Python :: 2.7
Classifier: Topic :: Documentation
Classifier: Topic :: Documentation :: Sphinx
Requires-Dist: Sphinx (>=0.6)
Requires-Dist: recommonmark
Requires-Dist: sphinxcontrib-httpdomain
